yxf/__init__.py
yxf/__main__.py
yxf/xlsform.py
yxf-0.5.1.dist-info/licenses/LICENSE
yxf-0.5.1.dist-info/METADATA
yxf-0.5.1.dist-info/WHEEL
yxf-0.5.1.dist-info/entry_points.txt
yxf-0.5.1.dist-info/top_level.txt
yxf-0.5.1.dist-info/RECORD
