Metadata-Version: 2.4
Name: yxf
Version: 0.5.1
Summary: Convert from XLSForm to YAML and back
Author-email: Jonas Wagner <jonas@purpureus.net>
License-Expression: BSD-2-Clause
Project-URL: homepage, https://github.com/Sjlver/yxf
Project-URL: documentation, https://github.com/Sjlver/yxf
Project-URL: repository, https://github.com/Sjlver/yxf
Project-URL: Bug Tracker, https://github.com/Sjlver/yxf/issues
Keywords: xlsform,xlsx,odk,pyxform
Classifier: Topic :: Utilities
Classifier: Programming Language :: Python :: 3
Classifier: Operating System :: OS Independent
Requires-Python: >=3.9
License-File: LICENSE
Requires-Dist: markdown-it-py>=2.0
Requires-Dist: openpyxl>=3.0
Requires-Dist: strictyaml>=1.6
Dynamic: license-file
